README.rst
setup.py
Flask_uWSGI_WebSocket.egg-info/PKG-INFO
Flask_uWSGI_WebSocket.egg-info/SOURCES.txt
Flask_uWSGI_WebSocket.egg-info/dependency_links.txt
Flask_uWSGI_WebSocket.egg-info/not-zip-safe
Flask_uWSGI_WebSocket.egg-info/requires.txt
Flask_uWSGI_WebSocket.egg-info/top_level.txt
flask_uwsgi_websocket/__init__.py
flask_uwsgi_websocket/_async.py
flask_uwsgi_websocket/_asyncio.py
flask_uwsgi_websocket/_gevent.py
flask_uwsgi_websocket/_uwsgi.py
flask_uwsgi_websocket/websocket.py