Metadata-Version: 1.1
Name: Flask-uWSGI-WebSocket
Version: 0.6.1
Summary: High-performance WebSockets for your Flask apps powered by uWSGI.
Home-page: https://github.com/zeekay/flask_uwsgi_websocket
Author: Zach Kelling
Author-email: zk@monoid.io
License: MIT
Keywords: uwsgi flask websockets
Platform: any
Classifier: Environment :: Web Environment
Classifier: Intended Audience :: Developers
Classifier: License :: OSI Approved :: MIT License
Classifier: Operating System :: OS Independent
Classifier: Programming Language :: Python
Classifier: Topic :: Internet :: WWW/HTTP :: Dynamic Content
Classifier: Topic :: Software Development :: Libraries :: Python Modules
